dronevis/__init__.py
dronevis/__main__.py
dronevis/main_gui.py
dronevis/abstract/__init__.py
dronevis/abstract/abstract_model.py
dronevis/abstract/abstract_torch_model.py
dronevis/abstract/base_drone.py
dronevis/abstract/base_video_thread.py
dronevis/abstract/noop_model.py
dronevis/assets/__init__.py
dronevis/assets/backward.png
dronevis/assets/connect.png
dronevis/assets/down.png
dronevis/assets/forward.png
dronevis/assets/left.png
dronevis/assets/off.png
dronevis/assets/on.png
dronevis/assets/right.png
dronevis/assets/rotate_ccw.png
dronevis/assets/rotate_cw.png
dronevis/assets/up.png
dronevis/config/__init__.py
dronevis/config/general.py
dronevis/config/gui.py
dronevis/drone_connect/__init__.py
dronevis/drone_connect/command.py
dronevis/drone_connect/demo_drone.py
dronevis/drone_connect/drone.py
dronevis/drone_connect/navdata.py
dronevis/drone_connect/navdata_decode.py
dronevis/drone_connect/video.py
dronevis/models/__init__.py
dronevis/models/action_recognition.py
dronevis/models/cnn_face_detection.py
dronevis/models/croud_count.py
dronevis/models/depth_estimation.py
dronevis/models/dnn_face_detection.py
dronevis/models/face_detection.py
dronevis/models/faster_rcnn_torch.py
dronevis/models/gesture_recognition.py
dronevis/models/haar_face_detection.py
dronevis/models/hog_face_detection.py
dronevis/models/model_factory.py
dronevis/models/pose_mediapipe.py
dronevis/models/road_segmentation.py
dronevis/models/ssd_torch.py
dronevis/models/yolov5_torch.py
dronevis/models/yolov8.py
dronevis/ui/__init__.py
dronevis/ui/drone_cli.py
dronevis/ui/drone_gui.py
dronevis/ui/gesture_recognition_thread.py
dronevis/ui/gui_components.py
dronevis/utils/__init__.py
dronevis/utils/control_utils.py
dronevis/utils/general.py
dronevis-1.3.0.dist-info/LICENSE
dronevis-1.3.0.dist-info/METADATA
dronevis-1.3.0.dist-info/WHEEL
dronevis-1.3.0.dist-info/entry_points.txt
dronevis-1.3.0.dist-info/top_level.txt
dronevis-1.3.0.dist-info/RECORD
