Metadata-Version: 2.1
Name: dronevis
Version: 1.3.0
Summary: Full compatible drone library to automate computer vision algorithms on parrot drones.
Author-email: Ahmed Heakl <ahmed.heakl@ejust.edu.eg>
Project-URL: repository, https://github.com/ahmedheakl/drone-vis
Keywords: drone,computer vision,human tracking,object recognition,YOLO,human counting,face detection,mediapipe,pytorch,sockets,thread
Classifier: License :: OSI Approved :: MIT License
Classifier: Programming Language :: Python
Classifier: Programming Language :: Python :: 3
Requires-Python: >=3.7
License-File: LICENSE
Requires-Dist: imutils >=0.5.0
Requires-Dist: opencv-contrib-python
Requires-Dist: gluoncv >=0.10.5
Requires-Dist: matplotlib >=3.5.3
Requires-Dist: numpy
Requires-Dist: opencv-python >=4.6.0.66
Requires-Dist: Pillow >=9.3.0
Requires-Dist: torch >=1.13.1
Requires-Dist: torchvision >=0.14.0
Requires-Dist: mediapipe >=0.8.0
Requires-Dist: rich
Requires-Dist: rich-argparse
Requires-Dist: termcolor
Requires-Dist: pyfiglet
Requires-Dist: coloredlogs
Requires-Dist: deep-sort-realtime
Requires-Dist: wget
Requires-Dist: googledrivedownloader
Requires-Dist: seaborn
Requires-Dist: ultralytics
Requires-Dist: transformers ~=4.31.0
Requires-Dist: ezcrowdcount
Requires-Dist: prefetch-generator
Requires-Dist: dlib
Provides-Extra: build
Requires-Dist: build ; extra == 'build'
Requires-Dist: twine ; extra == 'build'
Provides-Extra: dev
Requires-Dist: black ; extra == 'dev'
Requires-Dist: bumpver ; extra == 'dev'
